setup.py
wok_hooks/__hooks__.py
wok_hooks/__init__.py
wok_hooks/comments.py
wok_hooks/hook_comments.py
wok_hooks/hook_diaspora.py
wok_hooks/hook_digg.py
wok_hooks/hook_distribute.py
wok_hooks/hook_github.py
wok_hooks/hook_janitor.py
wok_hooks/hook_stackexchange.py
wok_hooks/hook_vcard.py
wok_hooks/hook_wikipedia.py
wok_hooks/misc.py
wok_hooks/timeline.py
wok_hooks.egg-info/PKG-INFO
wok_hooks.egg-info/SOURCES.txt
wok_hooks.egg-info/dependency_links.txt
wok_hooks.egg-info/requires.txt
wok_hooks.egg-info/top_level.txt