Metadata-Version: 1.1
Name: wok-hooks
Version: 0.1.0
Summary: Plugins for wok
Home-page: https://github.com/abbgrade/wok_hooks
Author: Steffen Kampmann
Author-email: steffen.kampmann@gmail.com
License: MIT
Platform: UNKNOWN
Classifier: Development Status :: 4 - Beta
Classifier: License :: OSI Approved :: MIT License
Classifier: Operating System :: POSIX
Classifier: Programming Language :: Python
